huscy/project_ethics/__init__.py
huscy/project_ethics/admin.py
huscy/project_ethics/apps.py
huscy/project_ethics/models.py
huscy/project_ethics/permissions.py
huscy/project_ethics/serializer.py
huscy/project_ethics/services.py
huscy/project_ethics/urls.py
huscy/project_ethics/views.py
huscy/project_ethics/migrations/0001_initial.py
huscy/project_ethics/migrations/0001_squashed_0010_alter_ethicsfile_ethics.py
huscy/project_ethics/migrations/0002_auto_20211101_0600.py
huscy/project_ethics/migrations/0003_alter_ethicfile_filehandle.py
huscy/project_ethics/migrations/0004_alter_ethicfile_filetype.py
huscy/project_ethics/migrations/0005_rename_ethicboard_ethicscommittee_and_more.py
huscy/project_ethics/migrations/0006_alter_ethic_options_and_more.py
huscy/project_ethics/migrations/0007_rename_ethic_ethics_alter_ethics_options_and_more.py
huscy/project_ethics/migrations/0008_alter_ethicfile_options_and_more.py
huscy/project_ethics/migrations/0009_rename_ethicfile_ethicsfile.py
huscy/project_ethics/migrations/0010_alter_ethicsfile_ethics.py
huscy/project_ethics/migrations/__init__.py
huscy.project_ethics-2.0.1.dist-info/LICENSE
huscy.project_ethics-2.0.1.dist-info/METADATA
huscy.project_ethics-2.0.1.dist-info/WHEEL
huscy.project_ethics-2.0.1.dist-info/top_level.txt
huscy.project_ethics-2.0.1.dist-info/RECORD
