Metadata-Version: 2.1
Name: huscy.project-ethics
Version: 2.0.1
Summary: Managing ethics and ethics files for projects in a human research context.
Home-page: UNKNOWN
Author: Stefan Bunde
Author-email: stefanbunde+git@posteo.de
License: AGPLv3+
Platform: UNKNOWN
Classifier: Development Status :: 5 - Production/Stable
Classifier: License :: OSI Approved :: GNU Affero General Public License v3 or later (AGPLv3+)
Classifier: Operating System :: OS Independent
Classifier: Programming Language :: Python
Classifier: Programming Language :: Python :: 3
Classifier: Programming Language :: Python :: 3 :: Only
Classifier: Programming Language :: Python :: 3.8
Classifier: Programming Language :: Python :: 3.9
Classifier: Programming Language :: Python :: 3.10
Classifier: Programming Language :: Python :: 3.11
Classifier: Programming Language :: Python :: 3.12
Classifier: Framework :: Django
Classifier: Framework :: Django :: 4.2
Classifier: Framework :: Django :: 5.0
Requires-Dist: huscy.projects
Provides-Extra: development
Requires-Dist: psycopg2-binary ; extra == 'development'
Provides-Extra: testing
Requires-Dist: tox ; extra == 'testing'
Requires-Dist: watchdog ; extra == 'testing'
